LICENSE
README.md
pyproject.toml
setup.py
pytori/__init__.py
pytori/_version.py
pytori/display.py
pytori/mathlib.py
pytori/normalform.py
pytori/plotting.py
pytori/series.py
pytori/tori.py
pytori/transforms.py
pytori/twiss.py
pytori.egg-info/PKG-INFO
pytori.egg-info/SOURCES.txt
pytori.egg-info/dependency_links.txt
pytori.egg-info/requires.txt
pytori.egg-info/top_level.txt
tests/test_base_series.py
tests/test_torus.py
tests/test_transforms.py