Metadata-Version: 2.4
Name: pytori
Version: 1.0.0
Summary: Transport of loops and tori in accelerator beam lines
Home-page: https://github.com/pbelange/pytori
Author: P. Belanger
License: Apache-2.0
Project-URL: Source Code, https://github.com/pbelange/pytori
Requires-Python: >=3.8
License-File: LICENSE
Requires-Dist: numpy>=1.0
Requires-Dist: pandas
Provides-Extra: tests
Requires-Dist: pytest; extra == "tests"
Dynamic: author
Dynamic: description
Dynamic: description-content-type
Dynamic: home-page
Dynamic: license
Dynamic: license-file
Dynamic: project-url
Dynamic: provides-extra
Dynamic: requires-dist
Dynamic: requires-python
Dynamic: summary
